build/lib/build/lib/build/lib/src/__init__.py
build/lib/build/lib/build/lib/src/test.py
build/lib/build/lib/build/lib/src/utilities.py
build/lib/build/lib/build/lib/src/vf.py
build/lib/build/lib/build/lib/src/virfinder_download.py
build/lib/build/lib/build/lib/src/virfinder_join_table.py
build/lib/build/lib/build/lib/src/virfinder_make_dbs.py
build/lib/build/lib/build/lib/src/configs/__init__.py
build/lib/build/lib/build/lib/src/configs/config.py
build/lib/build/lib/build/lib/src/configs/options.py
build/lib/build/lib/build/lib/src/run_module/CAT_radical.py
build/lib/build/lib/build/lib/src/run_module/__init__.py
build/lib/build/lib/build/lib/src/run_module/classify_radical.py
build/lib/build/lib/build/lib/src/run_module/draw_krona.py
build/lib/build/lib/build/lib/src/run_module/find_options.py
build/lib/build/lib/build/lib/src/run_module/vf_annotate.py
build/lib/build/lib/build/lib/src/run_module/vf_assemble.py
build/lib/build/lib/build/lib/src/run_module/vf_filter.py
build/lib/build/lib/build/lib/src/run_module/vf_kraken2.py
build/lib/build/lib/build/lib/src/run_module/vf_orf_predict.py
build/lib/build/lib/build/lib/src/run_module/vf_quantify.py
build/lib/build/lib/build/lib/src/run_module/vf_readsqc.py
build/lib/build/lib/build/lib/src/run_module/vf_report.py
build/lib/build/lib/build/lib/src/run_module/virus_divide.py
build/lib/build/lib/build/lib/src/test/__init__.py
build/lib/build/lib/src/__init__.py
build/lib/build/lib/src/test.py
build/lib/build/lib/src/utilities.py
build/lib/build/lib/src/vf.py
build/lib/build/lib/src/virfinder_download.py
build/lib/build/lib/src/virfinder_join_table.py
build/lib/build/lib/src/virfinder_make_dbs.py
build/lib/build/lib/src/configs/__init__.py
build/lib/build/lib/src/configs/config.py
build/lib/build/lib/src/configs/options.py
build/lib/build/lib/src/data/taxid2virus.txt
build/lib/build/lib/src/run_module/CAT_radical.py
build/lib/build/lib/src/run_module/__init__.py
build/lib/build/lib/src/run_module/classify_radical.py
IvFinder-0.0.1.dist-info/METADATA
IvFinder-0.0.1.dist-info/WHEEL
IvFinder-0.0.1.dist-info/entry_points.txt
IvFinder-0.0.1.dist-info/top_level.txt
IvFinder-0.0.1.dist-info/RECORD
